{
  "questions": [
    {
        "questionId": 1,
        "clientname": "amira",
        "questionContain": "ay klam fady ",
        "questionTime": "2002-02-02T00:00:00",
        "answers": [
            {
                "plantatoinname": "blkona",
                "answer": "kkkkkkkkkkkkkkkkkk",
                "date": "2003-06-06T00:00:00"
            },
            {
                "plantatoinname": "amira",
                "answer": "hhhhhhhhhhhhhhhh",
                "date": "2002-06-06T00:00:00"
            }
        ]
    },
    {
        "questionId": 4,
        "clientname": "amira",
        "questionContain": "ggggggggggggggg",
        "questionTime": "2002-02-02T00:00:00",
        "answers": []
    }
],
  "currentQuestionId" :12
}
